beetle_sass
