Metadata-Version: 1.1
Name: Beetle-Sass
Version: 1.2.0
Summary: Enables Beetle to handle Sass files
Home-page: https://github.com/Tenzer/beetle-sass
Author: Jeppe Toustrup
Author-email: jeppe@tenzer.dk
License: MIT
Platform: UNKNOWN
Classifier: Development Status :: 4 - Beta
Classifier: Intended Audience :: Developers
Classifier: Topic :: Text Processing :: Markup
Classifier: License :: OSI Approved :: MIT License
Classifier: Programming Language :: Python :: 2
Classifier: Programming Language :: Python :: 2.6
Classifier: Programming Language :: Python :: 2.7
Classifier: Programming Language :: Python :: 3
Classifier: Programming Language :: Python :: 3.3
Classifier: Programming Language :: Python :: 3.4
